cdk8s_plone/__init__.py
cdk8s_plone/py.typed
cdk8s_plone/_jsii/__init__.py
cdk8s_plone/_jsii/cdk8s-plone@0.1.17.jsii.tgz
cdk8s_plone-0.1.17.dist-info/LICENSE
cdk8s_plone-0.1.17.dist-info/METADATA
cdk8s_plone-0.1.17.dist-info/WHEEL
cdk8s_plone-0.1.17.dist-info/top_level.txt
cdk8s_plone-0.1.17.dist-info/RECORD
