Metadata-Version: 2.1
Name: cdk8s-plone
Version: 0.1.17
Summary: Provides a CMS Plone Backend and Frontend for Kubernetes with cdk8s
Home-page: https://github.com/bluedynamics/cdk8s-plone.git
Author: Jens W. Klein<jk@kleinundpartner.at>
License: Apache-2.0
Project-URL: Source, https://github.com/bluedynamics/cdk8s-plone.git
Classifier: Intended Audience :: Developers
Classifier: Operating System :: OS Independent
Classifier: Programming Language :: JavaScript
Classifier: Programming Language :: Python :: 3 :: Only
Classifier: Programming Language :: Python :: 3.9
Classifier: Programming Language :: Python :: 3.10
Classifier: Programming Language :: Python :: 3.11
Classifier: Typing :: Typed
Classifier: Development Status :: 5 - Production/Stable
Classifier: License :: OSI Approved
Requires-Python: ~=3.9
License-File: LICENSE
Requires-Dist: cdk8s-plus-30 <3.0.0,>=2.4.10
Requires-Dist: cdk8s <3.0.0,>=2.70.43
Requires-Dist: constructs <11.0.0,>=10.4.2
Requires-Dist: jsii <2.0.0,>=1.125.0
Requires-Dist: publication >=0.0.3
Requires-Dist: typeguard ==2.13.3
